[
  {
    "message": "Found a non-first page svg asset, ignoring it",
    "meta": {
      "name": "FREVO_DE_SEGUNDA_BONE_PIRATA-2",
      "entryPath": "/tmp/collection/carnaval bh 2025/FREVO_DE_SEGUNDA/FREVO_DE_SEGUNDA_BONE_PIRATA-2.svg"
    }
  },
  {
    "message": "Found a non-first page svg asset, ignoring it",
    "meta": {
      "name": "FREVO_DE_SEGUNDA_BONE_PIRATA-3",
      "entryPath": "/tmp/collection/carnaval bh 2025/FREVO_DE_SEGUNDA/FREVO_DE_SEGUNDA_BONE_PIRATA-3.svg"
    }
  },
  {
    "message": "Found a non-first page svg asset, ignoring it",
    "meta": {
      "name": "FREVO_DE_SEGUNDA_PETE_PIRATA-2",
      "entryPath": "/tmp/collection/carnaval bh 2025/FREVO_DE_SEGUNDA/FREVO_DE_SEGUNDA_PETE_PIRATA-2.svg"
    }
  },
  {
    "message": "Found a non-first page svg asset, ignoring it",
    "meta": {
      "name": "LIVIN_ON_A_PRAYER_SAX_TENOR-2",
      "entryPath": "/tmp/collection/carnaval bh 2025/LIVIN_ON_A_PRAYER/LIVIN_ON_A_PRAYER_SAX_TENOR-2.svg"
    }
  },
  {
    "message": "Found a non-first page svg asset, ignoring it",
    "meta": {
      "name": "MALHA_FUNK_PETE_PIRATA-2",
      "entryPath": "/tmp/collection/carnaval bh 2025/MALHA_FUNK/MALHA_FUNK_PETE_PIRATA-2.svg"
    }
  },
  {
    "message": "Found a non-first page svg asset, ignoring it",
    "meta": {
      "name": "RECONVEXO_FLAUTA-2",
      "entryPath": "/tmp/collection/carnaval bh 2025/RECONVEXO/RECONVEXO_FLAUTA-2.svg"
    }
  },
  {
    "message": "Found a non-first page svg asset, ignoring it",
    "meta": {
      "name": "RECONVEXO_SAX_ALTO-2",
      "entryPath": "/tmp/collection/carnaval bh 2025/RECONVEXO/RECONVEXO_SAX_ALTO-2.svg"
    }
  },
  {
    "message": "Found a non-first page svg asset, ignoring it",
    "meta": {
      "name": "SINA_FLAUTA-2",
      "entryPath": "/tmp/collection/carnaval bh 2025/SINA/SINA_FLAUTA-2.svg"
    }
  },
  {
    "message": "Found a non-first page svg asset, ignoring it",
    "meta": {
      "name": "SINA_PETE_PIRATA-2",
      "entryPath": "/tmp/collection/carnaval bh 2025/SINA/SINA_PETE_PIRATA-2.svg"
    }
  },
  {
    "message": "Found a non-first page svg asset, ignoring it",
    "meta": {
      "name": "SINA_SAX_ALTO-2",
      "entryPath": "/tmp/collection/carnaval bh 2025/SINA/SINA_SAX_ALTO-2.svg"
    }
  },
  {
    "message": "Found a non-first page svg asset, ignoring it",
    "meta": {
      "name": "SINA_SAX_TENOR-2",
      "entryPath": "/tmp/collection/carnaval bh 2025/SINA/SINA_SAX_TENOR-2.svg"
    }
  },
  {
    "message": "Found a non-first page svg asset, ignoring it",
    "meta": {
      "name": "VAI_SACUDIR_VAI_ABALAR_BONE_PIRATA-2",
      "entryPath": "/tmp/collection/carnaval bh 2025/VAI_SACUDIR_VAI_ABALAR/VAI_SACUDIR_VAI_ABALAR_BONE_PIRATA-2.svg"
    }
  },
  {
    "message": "Found a non-first page svg asset, ignoring it",
    "meta": {
      "name": "VAI_SACUDIR_VAI_ABALAR_FLAUTA-2",
      "entryPath": "/tmp/collection/carnaval bh 2025/VAI_SACUDIR_VAI_ABALAR/VAI_SACUDIR_VAI_ABALAR_FLAUTA-2.svg"
    }
  },
  {
    "message": "Found a non-first page svg asset, ignoring it",
    "meta": {
      "name": "VAI_SACUDIR_VAI_ABALAR_SAX_ALTO-2",
      "entryPath": "/tmp/collection/carnaval bh 2025/VAI_SACUDIR_VAI_ABALAR/VAI_SACUDIR_VAI_ABALAR_SAX_ALTO-2.svg"
    }
  }
]